ciditel_utilities/__init__.py
ciditel_utilities/strings.py
ciditel_utilities/validate.py
utilities_test/__init__.py
utilities_test/ciditel_utilities.py
utilities_test/utilities.py
verificaciones/__init__.py
verificaciones/strings.py
verificaciones/validate.py
verificaciones-1.1.dist-info/LICENSE.txt
verificaciones-1.1.dist-info/METADATA
verificaciones-1.1.dist-info/WHEEL
verificaciones-1.1.dist-info/top_level.txt
verificaciones-1.1.dist-info/RECORD
