Metadata-Version: 2.1
Name: verificaciones
Version: 1.1
Summary: Verificaciones al usuario
License-File: LICENSE.txt
